maikol_utils/__init__.py
maikol_utils/config.py
maikol_utils/file_utils.py
maikol_utils/other_utils.py
maikol_utils/print_utils.py
maikol_utils/time_tracker.py
maikol_utils-0.8.0.dist-info/licenses/LICENSE
maikol_utils-0.8.0.dist-info/METADATA
maikol_utils-0.8.0.dist-info/WHEEL
maikol_utils-0.8.0.dist-info/top_level.txt
maikol_utils-0.8.0.dist-info/RECORD
