Metadata-Version: 2.4
Name: maikol-utils
Version: 0.8.0
Summary: Python module with some utils for every day code that I've seen usefull lately while working. Print, print colors, print warnings, print errors, save files, load files, clear bash
Author: Miquel Gómez
License: MIT
Project-URL: Homepage, https://github.com/MiquelGomezCorral/maikol-utils/
Project-URL: Miquel, https://miquelgc.net
Requires-Python: >=3.7
License-File: LICENSE
Requires-Dist: natsort>=8.4.0
Dynamic: license-file
